Metadata-Version: 2.1
Name: data_science_test123
Version: 0.1.0
Summary: A small example package for data science tools
Author: Ahmed
Author-email: ahmed.asaad.refaei@gmail.com
Classifier: Programming Language :: Python :: 3
Classifier: License :: OSI Approved :: MIT License
Classifier: Operating System :: OS Independent
Requires-Python: >=3.10
Requires-Dist: numpy
Requires-Dist: pandas
Requires-Dist: scikit-learn
